{
  "db_name": "PostgreSQL",
  "query": "\n                    INSERT INTO score (chatter_id, channel_id, score, updated_at)\n                    SELECT \n                        chatter_id,\n                        channel_id,\n                        COUNT(*) as score,\n                        NOW() as updated_at\n                    FROM score_event\n                    GROUP BY chatter_id, channel_id\n                    ON CONFLICT (chatter_id, channel_id)\n                    DO UPDATE SET\n                        score = EXCLUDED.score,\n                        updated_at = EXCLUDED.updated_at\n                    ",
  "describe": {
    "columns": [],
    "parameters": {
      "Left": []
    },
    "nullable": []
  },
  "hash": "bc25aa23fcb76862a0cb164b2dc1b63ab16032e3c1c1b3cc8b2bec8e3752453c"
}
